{
    "name": "pxt-geometry",
    "description": "",
    "dependencies": {
        "device": "*",
        "pxt-trig": "github:eanders-ms/pxt-trig#65fbb2f976d173799dce026c5b7a9a0f814039ee"
    },
    "files": [
        "main.blocks",
        "main.ts",
        "README.md",
        "vec2.ts",
        "vec3.ts",
        "vec4.ts",
        "mat4.ts",
        "mat2.ts"
    ],
    "testFiles": [
        "test.ts"
    ],
    "targetVersions": {
        "target": "1.0.16",
        "targetId": "arcade"
    },
    "supportedTargets": [
        "arcade"
    ],
    "preferredEditor": "tsprj"
}
